foldifyai/__init__.py
foldifyai/analyze.py
foldifyai/cli.py
foldifyai/utils.py
foldifyai-0.1.33.dist-info/licenses/LICENSE
foldifyai-0.1.33.dist-info/METADATA
foldifyai-0.1.33.dist-info/WHEEL
foldifyai-0.1.33.dist-info/entry_points.txt
foldifyai-0.1.33.dist-info/top_level.txt
foldifyai-0.1.33.dist-info/RECORD
